config.py
mingli_mcp.py
core/__init__.py
core/base_system.py
core/birth_info.py
core/chart_result.py
core/exceptions.py
mingli_mcp-1.0.13.dist-info/licenses/LICENSE
systems/__init__.py
systems/astrology/__init__.py
systems/bazi/__init__.py
systems/bazi/bazi_system.py
systems/bazi/formatter.py
systems/bazi/lib/__init__.py
systems/bazi/lib/bazi.py
systems/bazi/lib/common.py
systems/bazi/lib/convert.py
systems/bazi/lib/datas.py
systems/bazi/lib/ganzhi.py
systems/ziwei/__init__.py
systems/ziwei/formatter.py
systems/ziwei/ziwei_system.py
transports/__init__.py
transports/base_transport.py
transports/http_transport.py
transports/stdio_transport.py
utils/__init__.py
utils/formatters.py
utils/metrics.py
utils/rate_limiter.py
utils/validators.py
mingli_mcp-1.0.13.dist-info/METADATA
mingli_mcp-1.0.13.dist-info/WHEEL
mingli_mcp-1.0.13.dist-info/entry_points.txt
mingli_mcp-1.0.13.dist-info/top_level.txt
mingli_mcp-1.0.13.dist-info/RECORD
