Metadata-Version: 2.4
Name: mingli-mcp
Version: 1.0.13
Summary: 命理MCP服务 - 支持紫微斗数、八字等多种命理系统
Author-email: spyfree <srlixin@gmail.com>
License: MIT
Project-URL: Homepage, https://github.com/spyfree/mingli-mcp
Project-URL: Repository, https://github.com/spyfree/mingli-mcp
Project-URL: Documentation, https://github.com/spyfree/mingli-mcp/blob/main/README.md
Project-URL: Issues, https://github.com/spyfree/mingli-mcp/issues
Keywords: mcp,ziwei,bazi,fortune,astrology
Classifier: Development Status :: 4 - Beta
Classifier: Intended Audience :: Developers
Classifier: License :: OSI Approved :: MIT License
Classifier: Programming Language :: Python :: 3
Classifier: Programming Language :: Python :: 3.10
Classifier: Programming Language :: Python :: 3.11
Classifier: Programming Language :: Python :: 3.12
Classifier: Programming Language :: Python :: 3.13
Requires-Python: >=3.10
License-File: LICENSE
Requires-Dist: iztro-py>=0.3.1
Requires-Dist: lunar_python>=1.4.7
Requires-Dist: bidict>=0.23.0
Requires-Dist: colorama>=0.4.6
Requires-Dist: python-dateutil>=2.8.0
Requires-Dist: python-dotenv>=1.0.0
Requires-Dist: fastapi>=0.104.0
Requires-Dist: uvicorn[standard]>=0.24.0
Provides-Extra: dev
Requires-Dist: pytest>=7.0.0; extra == "dev"
Requires-Dist: pytest-cov>=4.0.0; extra == "dev"
Requires-Dist: pytest-asyncio>=0.21.0; extra == "dev"
Requires-Dist: black>=23.0.0; extra == "dev"
Requires-Dist: flake8>=6.0.0; extra == "dev"
Requires-Dist: mypy>=1.0.0; extra == "dev"
Requires-Dist: pylint>=2.17.0; extra == "dev"
Requires-Dist: isort>=5.12.0; extra == "dev"
Dynamic: license-file
